hello_verilog/DD_TUT_1_2023_template/half_adder.v
module half_adder(input A,input B,output C1,output S);
    assign S = (!A && B) || (A && !B);
    assign C1 = (A && B);
endmodule

hello_verilog/DD_TUT_1_2023_template/full_adder.v
`include "half_adder.v"
module full_adder(input A,input B,input C0,output C1,output S);
//    wire x1;
//    wire a1,a2,a3;
//    wire o1;
//    xor xor1 (x1,A,B);
//    xor xor2 (S,x1,C0);

//    and and1 (a1,A,B);
//    and and2 (a2,B,C0);
//    and and3 (a3,A,C0);

//    or or1(o1,a1,a2);
//    or or2(C1,o1,a3);

//or via different method
// assign S = A ^ B ^ C0;
// assign C1 = (A&&B)||(B&&C0)||(C0&&A);


wire CMID;
wire w1,w2;
half_adder h1(A,B,CMID,W1);
half_adder h2(C0,W1,W2,S);
or o1(C1,CMID,W1);


endmodule

hello_verilog/DD_TUT_1_2023_template/testbench_fa.v
`include "full_adder.v"
module t_function;
    wire S,C1;
    reg A,B,C0;
    parameter stop_time = 100;
    full_adder fa(A,B,C0,C1,S);
    initial #stop_time $finish;
        initial begin
            $dumpfile("out.vcd");
            $dumpvars(0,t_function);
                A=0;B=0;C0=0;
            #10 A=1;B=0;C0=0;
            #10 A=1;B=1;C0=0; 
            #10 A=0;B=1;C0=0;
            #10 A=0;B=0;C0=1;
            #10 A=1;B=0;C0=1;
            #10 A=1;B=1;C0=1; 
            #10 A=0;B=1;C0=1;
    end

    initial begin
        $monitor ("Time =%0d, A=%b, B=%b, C0=%b,C1=%b ,S=%b",$time,A,B,C0,C1,S);
    end
endmodule

hello_verilog/DD_TUT_1_2023_template/out.vcd
$date
	Fri Sep 22 09:40:57 2023
$end
$version
	Icarus Verilog
$end
$timescale
	1s
$end
$scope module t_function $end
$var wire 1 ! S $end
$var wire 1 " C1 $end
$var reg 1 # A $end
$var reg 1 $ B $end
$var reg 1 % C0 $end
$scope module fa $end
$var wire 1 # A $end
$var wire 1 $ B $end
$var wire 1 % C0 $end
$var wire 1 " C1 $end
$var wire 1 & W2 $end
$var wire 1 ' W1 $end
$var wire 1 ! S $end
$var wire 1 ( CMID $end
$scope module h1 $end
$var wire 1 # A $end
$var wire 1 $ B $end
$var wire 1 ( C1 $end
$var wire 1 ' S $end
$upscope $end
$scope module h2 $end
$var wire 1 % A $end
$var wire 1 ' B $end
$var wire 1 & C1 $end
$var wire 1 ! S $end
$upscope $end
$upscope $end
$upscope $end
$enddefinitions $end
#0
$dumpvars
0(
0'
0&
0%
0$
0#
0"
0!
$end
#10
1!
1"
1'
1#
#20
0!
0'
1(
1$
#30
1!
1'
0(
0#
#40
0"
1!
0'
0&
1%
0$
#50
0!
1&
1"
1'
1#
#60
1!
0&
0'
1(
1$
#70
0!
1&
1'
0(
0#
