hello_verilog/lab9/jhonson.v
module johnson_ctr  
  (  
    input clk,  
    input rstn,  
    output reg [3:0] out  
  );  
  genvar i;
  always @ (posedge clk) begin  
      if (!rstn)  
         out <= 1;  
      else begin  
        out[3] <= ~out[0];  
        out[0] <= out[1];
        out[1] <= out[2];
        out[2] <= out[3];
      end  
  end  
endmodule

hello_verilog/lab9/testbench_jhon.v
`include "jhonson.v"

module tb;    
  
  reg clk;  
  reg rstn;  
  wire [3:0] out;  
  
  johnson_ctr   u0 (.clk (clk),  
                .rstn (rstn),  
                .out (out));  
  
  always #10 clk = ~clk;  
  
  initial begin  
    {clk, rstn} <= 0;  
  
    $monitor ("T=%0t out=%b", $time, out);  
    repeat (2) @(posedge clk);  
    rstn <= 1;  
    repeat (15) @(posedge clk);  
    $finish;  
  end  

  initial begin 
    $dumpfile("out.vcd"); $dumpvars;
  end
endmodule

hello_verilog/lab9/out.vcd
$date
	Fri Nov 17 04:24:05 2023
$end
$version
	Icarus Verilog
$end
$timescale
	1s
$end
$scope module tb $end
$var wire 4 ! out [3:0] $end
$var reg 1 " clk $end
$var reg 1 # rstn $end
$scope module u0 $end
$var wire 1 " clk $end
$var wire 1 # rstn $end
$var reg 4 $ out [3:0] $end
$upscope $end
$upscope $end
$enddefinitions $end
$comment Show the parameter values. $end
$dumpall
$end
#0
$dumpvars
bx $
0#
0"
bx !
$end
#10
b1 !
b1 $
1"
#20
0"
#30
1#
1"
#40
0"
#50
b0 !
b0 $
1"
#60
0"
#70
b1000 !
b1000 $
1"
#80
0"
#90
b1100 !
b1100 $
1"
#100
0"
#110
b1110 !
b1110 $
1"
#120
0"
#130
b1111 !
b1111 $
1"
#140
0"
#150
b111 !
b111 $
1"
#160
0"
#170
b11 !
b11 $
1"
#180
0"
#190
b1 !
b1 $
1"
#200
0"
#210
b0 !
b0 $
1"
#220
0"
#230
b1000 !
b1000 $
1"
#240
0"
#250
b1100 !
b1100 $
1"
#260
0"
#270
b1110 !
b1110 $
1"
#280
0"
#290
b1111 !
b1111 $
1"
#300
0"
#310
b111 !
b111 $
1"
#320
0"
#330
b11 !
b11 $
1"
