hello_verilog/counter_tut/counter.v
module up_counter(input clk, reset, output[2:0] counter);
reg [2:0] counter_up;

// up counter
always @(posedge clk or reset)
begin
if(reset)
 counter_up <= 3'd0;
else
 if(counter_up == 3'd6 || counter_up == 3'd7)
    counter_up <= 3'd0;
    
 else counter_up <= counter_up + 3'd1;
end 
assign counter = counter_up;
endmodule

hello_verilog/counter_tut/testbench.v
`include "counter.v"
module upcounter_testbench();
reg clk, reset;
wire [2:0] counter;

up_counter dut(clk, reset, counter);
initial begin 
clk=0;
forever #5 clk=~clk;
end
initial begin
    $dumpfile("out.vcd");
    $dumpvars(0, upcounter_testbench);
reset=1;
#15;
reset=0;
#200;
$finish;
reset=0;
end
endmodule

hello_verilog/counter_tut/out.vcd
$date
	Wed Nov  1 22:07:53 2023
$end
$version
	Icarus Verilog
$end
$timescale
	1s
$end
$scope module upcounter_testbench $end
$var wire 3 ! counter [2:0] $end
$var reg 1 " clk $end
$var reg 1 # reset $end
$scope module dut $end
$var wire 1 " clk $end
$var wire 3 $ counter [2:0] $end
$var wire 1 # reset $end
$var reg 3 % counter_up [2:0] $end
$upscope $end
$upscope $end
$enddefinitions $end
#0
$dumpvars
b0 %
b0 $
1#
0"
b0 !
$end
#5
1"
#10
0"
#15
b1 !
b1 $
b1 %
1"
0#
#20
0"
#25
b10 !
b10 $
b10 %
1"
#30
0"
#35
b11 !
b11 $
b11 %
1"
#40
0"
#45
b100 !
b100 $
b100 %
1"
#50
0"
#55
b101 !
b101 $
b101 %
1"
#60
0"
#65
b110 !
b110 $
b110 %
1"
#70
0"
#75
b0 !
b0 $
b0 %
1"
#80
0"
#85
b1 !
b1 $
b1 %
1"
#90
0"
#95
b10 !
b10 $
b10 %
1"
#100
0"
#105
b11 !
b11 $
b11 %
1"
#110
0"
#115
b100 !
b100 $
b100 %
1"
#120
0"
#125
b101 !
b101 $
b101 %
1"
#130
0"
#135
b110 !
b110 $
b110 %
1"
#140
0"
#145
b0 !
b0 $
b0 %
1"
#150
0"
#155
b1 !
b1 $
b1 %
1"
#160
0"
#165
b10 !
b10 $
b10 %
1"
#170
0"
#175
b11 !
b11 $
b11 %
1"
#180
0"
#185
b100 !
b100 $
b100 %
1"
#190
0"
#195
b101 !
b101 $
b101 %
1"
#200
0"
#205
b110 !
b110 $
b110 %
1"
#210
0"
#215
b0 !
b0 $
b0 %
1"
